{
    "database":{
        "user":"root",
        "passwd":"123456",
        "host":"127.0.0.1:3306",
        "dbname":"bilibili",
        "maxOpenConn":90
    },
    
    "videoCrawler":{
        "maxCrawlerNum":1000,
        "isDaemon":false,
        "startAid":1,
        "endAid":35000000
    },

    "network":{
        "useProxy":true,
        "userAgent":"Mozilla/5.0 (Macintosh; Intel Mac OS X 10_14_1) AppleWebKit/537.36 (KHTML, like Gecko) Chrome/70.0.3538.77 Safari/537.36",
        "retryTimes":50
    }

}